newsflash/__init__.py
newsflash/app.py
newsflash/base.py
newsflash/cache.py
newsflash/fonts.py
newsflash/manage.py
newsflash/types.py
newsflash/callback/builder.py
newsflash/callback/caller.py
newsflash/callback/models.py
newsflash/callback/utils.py
newsflash/fonts/noto-serif/LICENSE
newsflash/fonts/noto-serif/NotoSerif.ttf
newsflash/web/__init__.py
newsflash/web/asgi.py
newsflash/web/settings.py
newsflash/web/urls.py
newsflash/web/wsgi.py
newsflash/web/accounts/__init__.py
newsflash/web/accounts/apps.py
newsflash/web/accounts/models.py
newsflash/web/accounts/urls.py
newsflash/web/accounts/views.py
newsflash/web/accounts/migrations/__init__.py
newsflash/web/accounts/static/accounts/styles.css
newsflash/web/accounts/templates/accounts/login.html
newsflash/web/app/__init__.py
newsflash/web/app/apps.py
newsflash/web/app/models.py
newsflash/web/app/urls.py
newsflash/web/app/views.py
newsflash/web/app/migrations/__init__.py
newsflash/web/app/static/app/chart_animations.css
newsflash/web/app/static/app/htmxIncludeChartDimensions.js
newsflash/web/app/static/app/input.css
newsflash/web/app/static/app/main_styles.css
newsflash/web/app/static/app/notifications.css
newsflash/web/app/static/app/output.css
newsflash/web/app/static/app/spinner.css
newsflash/web/app/templates/app/additional_tailwind.html
newsflash/web/app/templates/app/base.html
newsflash/web/app/templates/app/link.html
newsflash/web/app/templates/app/navbar.html
newsflash/web/app/templates/app/notifications.html
newsflash/web/app/templates/app/page.html
newsflash/web/app/templates/app/unauthorized.html
newsflash/web/app/templates/app/widgets/chart/chart.html
newsflash/web/app/templates/app/widgets/chart/container.html
newsflash/web/app/templates/app/widgets/chart/elements/line.html
newsflash/web/app/templates/app/widgets/chart/elements/path.html
newsflash/web/app/templates/app/widgets/chart/elements/rect.html
newsflash/web/app/templates/app/widgets/chart/elements/text.html
newsflash-0.1.28.dist-info/METADATA
newsflash-0.1.28.dist-info/WHEEL
newsflash-0.1.28.dist-info/entry_points.txt
newsflash-0.1.28.dist-info/licenses/LICENSE
newsflash-0.1.28.dist-info/RECORD
