Metadata-Version: 2.4
Name: newsflash
Version: 0.1.28
Summary: A new library for Python dashboards and data apps
License-File: LICENSE
Requires-Python: >=3.12
Requires-Dist: click>=8.3.0
Requires-Dist: django>=5.2.6
Requires-Dist: fonttools>=4.60.1
Requires-Dist: polars>=1.34.0
Requires-Dist: pydantic>=2.11.9
Requires-Dist: uvicorn>=0.38.0
